{"\uc0b0": 0, "\uc2dc\uc7a5": 1, "\uc218\uc601\uc7a5": 2, "\ub180\uc774\uacf5\uc6d0": 3, "\ubbf8\uc220\uad00": 4, "\ud074\ub7fd": 5, "\ud638\ud154": 6, "\ubc15\ubb3c\uad00": 7, "\ub3d9\ubb3c\uc6d0": 8, "\uc544\uc774\uc2a4\ub9c1\ud06c": 9, "\uc9c0\ud558\ucca0\uc5ed": 10, "\ud3ed\ud3ec": 11, "\ub180\uc774\ud130": 12, "\uc544\ucfe0\uc544\ub9ac\uc6c0": 13, "\uc808": 14, "\ub2e4\ub9ac": 15, "\uc1fc\ud551\ubab0": 16, "\uacf5\uc6d0": 17, "\uacf5\ud56d": 18, "\uad50\ud68c": 19, "\uad81\uad90": 20, "\uc131\ub2f9": 21, "\ubcfc\ub9c1\uc7a5": 22}